CHANGELOG.md
COPYING.txt
MANIFEST.in
README.rst
setup.cfg
setup.py
rattail_mailchimp/__init__.py
rattail_mailchimp/_version.py
rattail_mailchimp/commands.py
rattail_mailchimp/config.py
rattail_mailchimp/emails.py
rattail_mailchimp.egg-info/PKG-INFO
rattail_mailchimp.egg-info/SOURCES.txt
rattail_mailchimp.egg-info/dependency_links.txt
rattail_mailchimp.egg-info/entry_points.txt
rattail_mailchimp.egg-info/not-zip-safe
rattail_mailchimp.egg-info/requires.txt
rattail_mailchimp.egg-info/top_level.txt
rattail_mailchimp/db/__init__.py
rattail_mailchimp/db/model.py
rattail_mailchimp/db/alembic/versions/805181d09df7_initial_tables.py
rattail_mailchimp/importing/__init__.py
rattail_mailchimp/importing/mailchimp.py
rattail_mailchimp/importing/model.py